Workbook

Sheet README
A1: Ocean Accounting Clinic: OESA
A2: Account Template
A4: How to use this file
A5: Fill in the yellow cells with your country's data.
A6: White cells with formulas will calculate automatically.
A7: See the Glossary sheet for definitions of all terms and abbreviations.
A8: See the Instructions sheet (if present) for detailed step-by-step guidance.

Sheet Scope Definition
A1: Step 1-2: Define Scope and Classify Activities
A2: Fill in your national industries and mark whether they are in scope.
A4: Ocean Economy Group | B4: National Industry | C4: ISIC Code | D4: In Scope (Y/N) | E4: Notes
A5: Living Resources
A6: Living Resources | B6: Marine fishing | C6: 0311
A7: Living Resources | B7: Marine aquaculture | C7: 0321
A8: Living Resources | B8: Fish processing | C8: 1020
A9: Living Resources
A10: Marine Minerals
A11: Marine Minerals | B11: Offshore oil & gas extraction | C11: 0610
A12: Marine Minerals | B12: Marine mining | C12: 0810
A13: Marine Minerals | B13: Salt extraction | C13: 0893
A14: Marine Minerals
A15: Marine Construction
A16: Marine Construction | B16: Port & harbour construction | C16: 4290
A17: Marine Construction | B17: Coastal protection works | C17: 4290
A18: Marine Construction | B18: Submarine cable laying | C18: 4220
A19: Marine Construction
A20: Ship and Boat Building
A21: Ship and Boat Building | B21: Shipbuilding | C21: 3011
A22: Ship and Boat Building | B22: Boat building | C22: 3012
A23: Ship and Boat Building | B23: Ship repair & maintenance | C23: 3315
A24: Ship and Boat Building
A25: Marine Transport
A26: Marine Transport | B26: Ocean freight transport | C26: 5012
A27: Marine Transport | B27: Coastal passenger transport | C27: 5011
A28: Marine Transport | B28: Port & terminal operations | C28: 5222
A29: Marine Transport | B29: Marine cargo handling | C29: 5224
A30: Marine Transport
A31: Coastal Tourism
A32: Coastal Tourism | B32: Accommodation (coastal) | C32: 5510
A33: Coastal Tourism | B33: Food & beverage (coastal) | C33: 5610
A34: Coastal Tourism | B34: Recreation & sports (marine) | C34: 9319
A35: Coastal Tourism | B35: Travel agencies (marine tours) | C35: 7911
A36: Coastal Tourism

Sheet Ocean Partials
A1: Step 4: Ocean Economy Partials
A2: Enter the ocean partial for each industry. Use South Africa examples as a starting point.
A4: Industry | B4: ISIC Code | C4: Ocean Partial (%) | D4: Data Source | E4: Confidence (RAG)
A5: Marine fishing | B5: 0311 | C5: 1 | D5: By definition | E5: Green
A6: Marine aquaculture | B6: 0321 | C6: 1 | D6: By definition | E6: Green
A7: Fish processing | B7: 1020 | C7: 0.85 | D7: Industry survey | E7: Amber
A8: Offshore oil & gas | B8: 0610 | C8: 1 | D8: By definition | E8: Green
A9: Marine mining | B9: 0810 | C9: 0.3 | D9: Expert estimate | E9: Red
A10: Salt extraction | B10: 0893 | C10: 0.5 | D10: Expert estimate | E10: Amber
A11: Port construction | B11: 4290 | C11: 0.6 | D11: Budget records | E11: Amber
A12: Coastal protection | B12: 4290 | C12: 1 | D12: By definition | E12: Green
A13: Shipbuilding | B13: 3011 | C13: 1 | D13: By definition | E13: Green
A14: Boat building | B14: 3012 | C14: 1 | D14: By definition | E14: Green
A15: Ship repair | B15: 3315 | C15: 0.8 | D15: Industry survey | E15: Amber
A16: Ocean freight | B16: 5012 | C16: 1 | D16: By definition | E16: Green
... A22: Travel agencies (marine) | B22: 7911 | C22: 0.25 | D22: Expert estimate | E22: Red

Sheet Output Table
A1: OESA: Gross Output by Ocean Economy Group
A2: Enter National Output and Ocean Partial. Ocean Output is calculated automatically.
A4: Ocean Economy Group | B4: National Output (USD million) | C4: Ocean Partial | D4: Ocean Output (USD million)
A5: Living Resources | D5: =B5*C5
A6: Marine Minerals | D6: =B6*C6
A7: Marine Construction | D7: =B7*C7
A8: Ship and Boat Building | D8: =B8*C8
A9: Marine Transport | D9: =B9*C9
A10: Coastal Tourism | D10: =B10*C10
A11: TOTAL | D11: =SUM(D5:D10)

Sheet GVA Table
A1: OESA: Gross Value Added
A2: Ocean Output links from Output Table. Enter Ocean IC. GVA = Output - IC.
A4: Ocean Economy Group | B4: Ocean Output (USD million) | C4: Ocean IC (USD million) | D4: Ocean GVA (USD million) | E4: Employment
A5: Living Resources | B5: ='Output Table'!D5 | D5: =B5-C5
A6: Marine Minerals | B6: ='Output Table'!D6 | D6: =B6-C6
A7: Marine Construction | B7: ='Output Table'!D7 | D7: =B7-C7
A8: Ship and Boat Building | B8: ='Output Table'!D8 | D8: =B8-C8
A9: Marine Transport | B9: ='Output Table'!D9 | D9: =B9-C9
A10: Coastal Tourism | B10: ='Output Table'!D10 | D10: =B10-C10
A11: TOTAL | B11: =SUM(B5:B10) | C11: =SUM(C5:C10) | D11: =SUM(D5:D10) | E11: =SUM(E5:E10)

Sheet Summary
A1: OESA Summary
A3: Key Metric | B3: Value
A4: Total Ocean GVA (USD million) | B4: ='GVA Table'!D11
A5: National GDP (USD million)
A6: Ocean % of GDP | B6: =IF(B5>0,B4/B5,0)
A8: Ocean Economy Group | B8: Ocean GVA (USD million) | C8: Employment
A9: Living Resources | B9: ='GVA Table'!D5 | C9: ='GVA Table'!E5
A10: Marine Minerals | B10: ='GVA Table'!D6 | C10: ='GVA Table'!E6
A11: Marine Construction | B11: ='GVA Table'!D7 | C11: ='GVA Table'!E7
A12: Ship and Boat Building | B12: ='GVA Table'!D8 | C12: ='GVA Table'!E8
A13: Marine Transport | B13: ='GVA Table'!D9 | C13: ='GVA Table'!E9
A14: Coastal Tourism | B14: ='GVA Table'!D10 | C14: ='GVA Table'!E10
A15: TOTAL | B15: =SUM(B9:B14) | C15: =SUM(C9:C14)

Sheet Instructions
A1: How to Use This Template
A3: Step 1: Go to the 'Scope Definition' sheet. List your country's ocean-related industries and classify them into groups.
A4: Step 2: Mark each industry as in scope (Y) or out of scope (N).
A5: Step 3: Go to the 'Ocean Partials' sheet. For each in-scope industry, enter the ocean partial (the share of that industry attributable to the ocean).
A6: Step 4: Go to the 'Output Table' sheet. Enter national gross output for each ocean economy group. The ocean output will be calculated automatically.
A7: Step 5: Go to the 'GVA Table' sheet. Enter intermediate consumption (IC) for each group. GVA = Output - IC will be calculated automatically.
A8: Step 6: Go to the 'Summary' sheet. Enter your national GDP. The ocean share of GDP will be calculated automatically.
A10: Tips:
A11: - Yellow cells are for your input.
A12: - White cells with formulas will calculate automatically.
A13: - Use the RAG column in Ocean Partials to indicate your confidence: Green (high), Amber (medium), Red (low).
A14: - Refer to GOAP Technical Guidance for detailed methodology.

Sheet Glossary
A1: Glossary of Terms and Abbreviations
A3: Term / Abbreviation | B3: Full Name | C3: Definition | D3: Unit
A4: GVA | B4: Gross Value Added | C4: Total output minus intermediate consumption. The value an industry adds to the economy. | D4: Currency (e.g., USD, local currency)
A5: GDP | B5: Gross Domestic Product | C5: Total value of goods and services produced in a country. Sum of GVA across all industries plus taxes minus subsidies. | D5: Currency
A6: IC | B6: Intermediate Consumption | C6: The value of goods and services consumed as inputs during production (e.g., fuel, raw materials, purchased services). Does not include fixed assets. | D6: Currency
A7: Output | B7: Gross Output | C7: Total value of goods and services produced by an industry before deducting input costs. Also called gross sales or turnover. | D7: Currency
A8: SUT | B8: Supply-Use Tables | C8: Statistical tables from the national accounts showing what each industry produces (supply) and what each industry consumes (use). Published by the National Statistical Office.
A9: SNA | B9: System of National Accounts | C9: The international statistical standard for measuring economic activity. Published by the UN. The basis for GDP calculation.
A10: SEEA-EA | B10: System of Environmental-Economic Accounting - Ecosystem Accounting | C10: The international statistical standard for measuring ecosystems, their condition, and the services they provide.
A11: OESA | B11: Ocean Economy Satellite Account | C11: A satellite account that reorganizes national accounts to identify the market-based ocean economy. Reports GDP-compatible indicators.
A12: OTSA | B12: Ocean Tourism Satellite Account | C12: A satellite account focused on coastal and marine tourism's economic contribution. A subset of OESA.
A13: Partial | B13: Ocean Economy Partial | C13: The share (0 to 1) of a mixed industry's output that is ocean-related. For example, if 30% of construction is coastal, the partial is 0.30. | D13: Proportion (0 to 1)
A14: CI | B14: Condition Index | C14: A normalized score from 0 (fully degraded) to 1 (reference/healthy condition). Used in SEEA-EA condition accounts. | D14: Index (0 to 1)
A15: NCP | B15: Net Carbon Production | C15: The rate at which an ecosystem sequesters carbon dioxide per unit area per year. | D15: Mg CO2/ha/yr
A16: SCC | B16: Social Cost of Carbon | C16: An estimate of the economic damage caused by emitting one additional tonne of CO2. Used to value carbon sequestration. | D16: USD per Mg CO2
A17: Mg CO2 | B17: Megagrams of CO2 | C17: Metric tonnes of carbon dioxide. 1 Mg = 1 tonne = 1,000 kg. | D17: Mass
A18: ha | B18: Hectares | C18: Unit of area. 1 hectare = 10,000 square metres = 0.01 square kilometres. | D18: Area
A19: kg/yr | B19: Kilograms per year | C19: Physical quantity measured in kilograms over one year. | D19: Mass per time
A20: USD million | B20: United States Dollars, millions | C20: Monetary values expressed in millions of US dollars. For example, USD 132.5 million = USD 132,500,000. | D20: Currency
A21: R million | B21: South African Rand, millions | C21: Monetary values in the South Africa example are in millions of Rand. | D21: Currency
A22: ISIC | B22: International Standard Industrial Classification | C22: The UN classification system for economic activities. Used to map industries to ocean economy groups.
A23: SIC | B23: Standard Industrial Classification | C23: National classification system for economic activities. Varies by country but based on ISIC.
A24: EEZ | B24: Exclusive Economic Zone | C24: Maritime zone extending 200 nautical miles from a country's coastline, within which the country has rights to marine resources.
A25: RAG | B25: Red-Amber-Green | C25: A confidence rating system. Green = high confidence (direct evidence). Amber = moderate (proxy data). Red = low (sparse evidence).
